<topRoot childAction="" dn="" status=""><configShardLocator childAction="" dn="" lcOwn="local" modTs="never" shard="23" status=""/><polUni annotation="" childAction="" dn="" extMngdBy="" lcOwn="local" modTs="never" monPolDn="" name="" nameAlias="" ownerKey="" ownerTag="" status="" uid="0" userdom="all"><ctrlrInst annotation="" childAction="" dn="" extMngdBy="" lcOwn="local" modTs="never" monPolDn="" name="" nameAlias="" ownerKey="" ownerTag="" status="" uid="0" userdom="all"><fabricExtRoutableSubnetCont childAction="deleteNonPresent" descr="" dn="" lcOwn="local" modTs="2020-06-12T17:39:05.910+03:00" monPolDn="uni/fabric/monfab-default" name="default" nameAlias="" ownerKey="" ownerTag="" status=""><fabricExtRoutablePodSubnetCont childAction="deleteNonPresent" descr="" dn="" lcOwn="local" modTs="2022-12-12T18:25:22.529+03:00" monPolDn="uni/fabric/monfab-default" name="" nameAlias="" podId="1" status=""><fabricExtRoutableAnycastIp addr="10.99.6.165/32" childAction="deleteNonPresent" descr="" dn="" lcOwn="local" modTs="2022-12-12T18:25:22.529+03:00" name="" nameAlias="" ownerKey="" ownerTag="" status=""/><fabricExtRoutableSubnet childAction="deleteNonPresent" descr="" dn="" ip="10.99.6.160/27" lcOwn="local" modTs="2022-12-12T18:25:22.529+03:00" name="" nameAlias="" status=""><fabricExtRoutablePool childAction="deleteNonPresent" descr="" dn="" endIp="10.99.6.190" freeIPs="67108860" freeIpCount="24" id="1" lcOwn="local" modTs="2024-07-12T04:07:50.526+03:00" name="" nameAlias="" startIp="10.99.6.165" status=""/></fabricExtRoutableSubnet></fabricExtRoutablePodSubnetCont><fabricExtRoutablePodSubnetCont childAction="deleteNonPresent" descr="" dn="" lcOwn="local" modTs="2022-12-12T18:31:15.313+03:00" monPolDn="uni/fabric/monfab-default" name="" nameAlias="" podId="2" status=""><fabricExtRoutableAnycastIp addr="10.102.6.165/32" childAction="deleteNonPresent" descr="" dn="" lcOwn="local" modTs="2022-12-12T18:31:15.313+03:00" name="" nameAlias="" ownerKey="" ownerTag="" status=""/><fabricExtRoutableSubnet childAction="deleteNonPresent" descr="" dn="" ip="10.102.6.160/27" lcOwn="local" modTs="2022-12-12T18:31:15.313+03:00" name="" nameAlias="" status=""><fabricExtRoutablePool childAction="deleteNonPresent" descr="" dn="" endIp="10.102.6.190" freeIPs="67108860" freeIpCount="24" id="1" lcOwn="local" modTs="2024-07-12T04:07:50.526+03:00" name="" nameAlias="" startIp="10.102.6.165" status=""/></fabricExtRoutableSubnet></fabricExtRoutablePodSubnetCont></fabricExtRoutableSubnetCont></ctrlrInst></polUni><resCont childAction="deleteNonPresent" dn="" lcOwn="local" modTs="2019-03-11T04:33:13.645+03:00" status=""/><identCont childAction="deleteNonPresent" dn="" isUniSyncDone="yes" lcOwn="local" modTs="2024-07-12T04:08:03.658+03:00" status=""><identSubj childAction="deleteNonPresent" dn="" lcOwn="local" modTs="2022-12-12T18:31:15.313+03:00" name="iddhcp" nameAlias="" oDn="" profile="large" status=""><identNs childAction="deleteNonPresent" descr="" dn="" lcOwn="local" modTs="2022-12-12T18:31:15.313+03:00" name="nsdhcp2" nameAlias="" oDn="" ownerKey="" ownerTag="" status="" usageStatus="green"><identBlock32 childAction="deleteNonPresent" descr="" dn="" from="5449730" lcOwn="local" modTs="2022-12-12T18:31:15.313+03:00" name="" nameAlias="" size="2045" status="" to="5451774" type="include" usageStatus="green"><identSegment32 allocSize="0" childAction="deleteNonPresent" dn="" from="5450370" id="11" instSize="0" lastAssigned="0" lcOwn="local" modTs="2022-12-12T18:31:15.313+03:00" operSt="uninitialized" profile="large" size="64" status="" to="5450433" usageStatus="green"/><identSegment32 allocSize="0" childAction="deleteNonPresent" dn="" from="5450946" id="20" instSize="0" lastAssigned="0" lcOwn="local" modTs="2022-12-12T18:31:15.313+03:00" operSt="uninitialized" profile="large" size="64" status="" to="5451009" usageStatus="green"/><identSegment32 allocSize="0" childAction="deleteNonPresent" dn="" from="5450178" id="8" instSize="0" lastAssigned="0" lcOwn="local" modTs="2022-12-12T18:31:15.313+03:00" operSt="uninitialized" profile="large" size="64" status="" to="5450241" usageStatus="green"/><identSegment32 allocSize="0" childAction="deleteNonPresent" dn="" from="5450242" id="9" instSize="0" lastAssigned="0" lcOwn="local" modTs="2022-12-12T18:31:15.313+03:00" operSt="uninitialized" profile="large" size="64" status="" to="5450305" usageStatus="green"/><identSegment32 allocSize="0" childAction="deleteNonPresent" dn="" from="5450434" id="12" instSize="0" lastAssigned="0" lcOwn="local" modTs="2022-12-12T18:31:15.313+03:00" operSt="uninitialized" profile="large" size="64" status="" to="5450497" usageStatus="green"/><identSegment32 allocSize="0" childAction="deleteNonPresent" dn="" from="5451330" id="26" instSize="0" lastAssigned="0" lcOwn="local" modTs="2022-12-12T18:31:15.313+03:00" operSt="uninitialized" profile="large" size="64" status="" to="5451393" usageStatus="green"/><identSegment32 allocSize="0" childAction="deleteNonPresent" dn="" from="5449794" id="2" instSize="0" lastAssigned="0" lcOwn="local" modTs="2022-12-12T18:31:15.313+03:00" operSt="uninitialized" profile="large" size="64" status="" to="5449857" usageStatus="green"/><identSegment32 allocSize="0" childAction="deleteNonPresent" dn="" from="5451649" id="31" instSize="0" lastAssigned="0" lcOwn="local" modTs="2022-12-12T18:31:15.313+03:00" operSt="uninitialized" profile="large" size="63" status="" to="5451711" usageStatus="green"/><identSegment32 allocSize="0" childAction="deleteNonPresent" dn="" from="5450754" id="17" instSize="0" lastAssigned="0" lcOwn="local" modTs="2022-12-12T18:31:15.313+03:00" operSt="uninitialized" profile="large" size="64" status="" to="5450817" usageStatus="green"/><identSegment32 allocSize="0" childAction="deleteNonPresent" dn="" from="5449922" id="4" instSize="0" lastAssigned="0" lcOwn="local" modTs="2022-12-12T18:31:15.313+03:00" operSt="uninitialized" profile="large" size="64" status="" to="5449985" usageStatus="green"/><identSegment32 allocSize="0" childAction="deleteNonPresent" dn="" from="5449858" id="3" instSize="0" lastAssigned="0" lcOwn="local" modTs="2022-12-12T18:31:15.313+03:00" operSt="uninitialized" profile="large" size="64" status="" to="5449921" usageStatus="green"/><identSegment32 allocSize="0" childAction="deleteNonPresent" dn="" from="5451010" id="21" instSize="0" lastAssigned="0" lcOwn="local" modTs="2022-12-12T18:31:15.313+03:00" operSt="uninitialized" profile="large" size="64" status="" to="5451073" usageStatus="green"/><identSegment32 allocSize="0" childAction="deleteNonPresent" dn="" from="5451586" id="30" instSize="0" lastAssigned="0" lcOwn="local" modTs="2022-12-12T18:31:15.313+03:00" operSt="uninitialized" profile="large" size="63" status="" to="5451648" usageStatus="green"/><identSegment32 allocSize="0" childAction="deleteNonPresent" dn="" from="5450050" id="6" instSize="0" lastAssigned="0" lcOwn="local" modTs="2022-12-12T18:31:15.313+03:00" operSt="uninitialized" profile="large" size="64" status="" to="5450113" usageStatus="green"/><identSegment32 allocSize="0" childAction="deleteNonPresent" dn="" from="5449730" id="1" instSize="0" lastAssigned="0" lcOwn="local" modTs="2022-12-12T18:31:15.313+03:00" operSt="uninitialized" profile="large" size="64" status="" to="5449793" usageStatus="green"/><identSegment32 allocSize="0" childAction="deleteNonPresent" dn="" from="5451138" id="23" instSize="0" lastAssigned="0" lcOwn="local" modTs="2022-12-12T18:31:15.313+03:00" operSt="uninitialized" profile="large" size="64" status="" to="5451201" usageStatus="green"/><identSegment32 allocSize="0" childAction="deleteNonPresent" dn="" from="5451202" id="24" instSize="0" lastAssigned="0" lcOwn="local" modTs="2022-12-12T18:31:15.313+03:00" operSt="uninitialized" profile="large" size="64" status="" to="5451265" usageStatus="green"/><identSegment32 allocSize="0" childAction="deleteNonPresent" dn="" from="5450306" id="10" instSize="0" lastAssigned="0" lcOwn="local" modTs="2022-12-12T18:31:15.313+03:00" operSt="uninitialized" profile="large" size="64" status="" to="5450369" usageStatus="green"/><identSegment32 allocSize="0" childAction="deleteNonPresent" dn="" from="5451712" id="32" instSize="0" lastAssigned="0" lcOwn="local" modTs="2022-12-12T18:31:15.313+03:00" operSt="uninitialized" profile="large" size="63" status="" to="5451774" usageStatus="green"/><identSegment32 allocSize="0" childAction="deleteNonPresent" dn="" from="5450626" id="15" instSize="0" lastAssigned="0" lcOwn="local" modTs="2022-12-12T18:31:15.313+03:00" operSt="uninitialized" profile="large" size="64" status="" to="5450689" usageStatus="green"/><identSegment32 allocSize="0" childAction="deleteNonPresent" dn="" from="5450818" id="18" instSize="0" lastAssigned="0" lcOwn="local" modTs="2022-12-12T18:31:15.313+03:00" operSt="uninitialized" profile="large" size="64" status="" to="5450881" usageStatus="green"/><identSegment32 allocSize="0" childAction="deleteNonPresent" dn="" from="5450562" id="14" instSize="0" lastAssigned="0" lcOwn="local" modTs="2022-12-12T18:31:15.313+03:00" operSt="uninitialized" profile="large" size="64" status="" to="5450625" usageStatus="green"/><identSegment32 allocSize="0" childAction="deleteNonPresent" dn="" from="5451458" id="28" instSize="0" lastAssigned="0" lcOwn="local" modTs="2022-12-12T18:31:15.313+03:00" operSt="uninitialized" profile="large" size="64" status="" to="5451521" usageStatus="green"/><identSegment32 allocSize="0" childAction="deleteNonPresent" dn="" from="5449986" id="5" instSize="0" lastAssigned="0" lcOwn="local" modTs="2022-12-12T18:31:15.313+03:00" operSt="uninitialized" profile="large" size="64" status="" to="5450049" usageStatus="green"/><identSegment32 allocSize="0" childAction="deleteNonPresent" dn="" from="5450498" id="13" instSize="0" lastAssigned="0" lcOwn="local" modTs="2022-12-12T18:31:15.313+03:00" operSt="uninitialized" profile="large" size="64" status="" to="5450561" usageStatus="green"/><identSegment32 allocSize="0" childAction="deleteNonPresent" dn="" from="5451074" id="22" instSize="0" lastAssigned="0" lcOwn="local" modTs="2022-12-12T18:31:15.313+03:00" operSt="uninitialized" profile="large" size="64" status="" to="5451137" usageStatus="green"/><identSegment32 allocSize="0" childAction="deleteNonPresent" dn="" from="5451394" id="27" instSize="0" lastAssigned="0" lcOwn="local" modTs="2022-12-12T18:31:15.313+03:00" operSt="uninitialized" profile="large" size="64" status="" to="5451457" usageStatus="green"/><identSegment32 allocSize="0" childAction="deleteNonPresent" dn="" from="5450690" id="16" instSize="0" lastAssigned="0" lcOwn="local" modTs="2022-12-12T18:31:15.313+03:00" operSt="uninitialized" profile="large" size="64" status="" to="5450753" usageStatus="green"/><identSegment32 allocSize="0" childAction="deleteNonPresent" dn="" from="5450114" id="7" instSize="0" lastAssigned="0" lcOwn="local" modTs="2022-12-12T18:31:15.313+03:00" operSt="uninitialized" profile="large" size="64" status="" to="5450177" usageStatus="green"/><identSegment32 allocSize="0" childAction="deleteNonPresent" dn="" from="5450882" id="19" instSize="0" lastAssigned="0" lcOwn="local" modTs="2022-12-12T18:31:15.313+03:00" operSt="uninitialized" profile="large" size="64" status="" to="5450945" usageStatus="green"/><identSegment32 allocSize="0" childAction="deleteNonPresent" dn="" from="5451266" id="25" instSize="0" lastAssigned="0" lcOwn="local" modTs="2022-12-12T18:31:15.313+03:00" operSt="uninitialized" profile="large" size="64" status="" to="5451329" usageStatus="green"/><identSegment32 allocSize="0" childAction="deleteNonPresent" dn="" from="5451522" id="29" instSize="0" lastAssigned="0" lcOwn="local" modTs="2022-12-12T18:31:15.313+03:00" operSt="uninitialized" profile="large" size="64" status="" to="5451585" usageStatus="green"/></identBlock32></identNs></identSubj></identCont></topRoot>